nanoqnt/__init__.py
nanoqnt/_version.py
nanoqnt/dispertech-logo.ico
nanoqnt/main.py
nanoqnt/model/__init__.py
nanoqnt/model/analyze_nanoqnt.py
nanoqnt/model/decorators.py
nanoqnt/model/exceptions.py
nanoqnt/stage_main.py
nanoqnt/util/__init__.py
nanoqnt/util/make_hdf5.py
nanoqnt/view/GUI/Icons/11813 - Amplifier.svg
nanoqnt/view/GUI/Icons/11814 - Atom.svg
nanoqnt/view/GUI/Icons/11815 - Battery.svg
nanoqnt/view/GUI/Icons/11816 - Orbit.svg
nanoqnt/view/GUI/Icons/11817 - Beaker.svg
nanoqnt/view/GUI/Icons/11818 - Black Hole.svg
nanoqnt/view/GUI/Icons/11819 - Bounce.svg
nanoqnt/view/GUI/Icons/11820 - Caliper.svg
nanoqnt/view/GUI/Icons/11821 - Catapult.svg
nanoqnt/view/GUI/Icons/11822 - Collision.svg
nanoqnt/view/GUI/Icons/11823 - Communicating Vessels.svg
nanoqnt/view/GUI/Icons/11824 - Cylinder.svg
nanoqnt/view/GUI/Icons/11825 - Dispersion.svg
nanoqnt/view/GUI/Icons/11826 - Elasticity.svg
nanoqnt/view/GUI/Icons/11827 - Electrical Circuit.svg
nanoqnt/view/GUI/Icons/11828 - Energy.svg
nanoqnt/view/GUI/Icons/11829 - Flask.svg
nanoqnt/view/GUI/Icons/11830 - Float.svg
nanoqnt/view/GUI/Icons/11831 - Fluid Mechanics.svg
nanoqnt/view/GUI/Icons/11832 - Force.svg
nanoqnt/view/GUI/Icons/11833 - Formula.svg
nanoqnt/view/GUI/Icons/11834 - Gears.svg
nanoqnt/view/GUI/Icons/11835 - Gravity.svg
nanoqnt/view/GUI/Icons/11836 - Gyroscope.svg
nanoqnt/view/GUI/Icons/11837 - Histogram.svg
nanoqnt/view/GUI/Icons/11838 - Law Of Motion.svg
nanoqnt/view/GUI/Icons/11839 - Magnet.svg
nanoqnt/view/GUI/Icons/11840 - Magnetic Field.svg
nanoqnt/view/GUI/Icons/11841 - Metronome.svg
nanoqnt/view/GUI/Icons/11842 - Micrometer.svg
nanoqnt/view/GUI/Icons/11843 - Molecule.svg
nanoqnt/view/GUI/Icons/11844 - Motion.svg
nanoqnt/view/GUI/Icons/11845 - Nuclear.svg
nanoqnt/view/GUI/Icons/11846 - Oscilloscope.svg
nanoqnt/view/GUI/Icons/11847 - Pendulum.svg
nanoqnt/view/GUI/Icons/11848 - Planet.svg
nanoqnt/view/GUI/Icons/11849 - Plasma Ball.svg
nanoqnt/view/GUI/Icons/11850 - Power.svg
nanoqnt-0.2.2.dist-info/LICENSE.md
nanoqnt-0.2.2.dist-info/METADATA
nanoqnt-0.2.2.dist-info/WHEEL
nanoqnt-0.2.2.dist-info/entry_points.txt
nanoqnt-0.2.2.dist-info/RECORD
